pyterrier_pisa-0.3.1.dist-info/RECORD
pyterrier_pisa-0.3.1.dist-info/WHEEL
pyterrier_pisa-0.3.1.dist-info/top_level.txt
pyterrier_pisa-0.3.1.dist-info/METADATA
pyterrier_pisa-0.3.1.dist-info/entry_points.txt
pyterrier_pisa-0.3.1.dist-info/LICENSE
pyterrier_pisa/__init__.py
pyterrier_pisa/cli.py
pyterrier_pisa/pisa_metadata_adapter.py
pyterrier_pisa/stopwords.py
pyterrier_pisa/indexers.py
pyterrier_pisa/pt_docs/index.rst
pyterrier_pisa-0.3.1.data/data/lib64/librapidcheck.a
pyterrier_pisa-0.3.1.data/data/lib64/cmake/spdlog/spdlogTargets.cmake
pyterrier_pisa-0.3.1.data/data/lib64/cmake/spdlog/spdlogConfigVersion.cmake
pyterrier_pisa-0.3.1.data/data/lib64/cmake/spdlog/spdlogConfig.cmake
pyterrier_pisa-0.3.1.data/data/lib64/pkgconfig/spdlog.pc
pyterrier_pisa-0.3.1.data/data/include/module.modulemap
pyterrier_pisa-0.3.1.data/data/include/wapopp.hpp
pyterrier_pisa-0.3.1.data/data/include/Porter2.hpp
pyterrier_pisa-0.3.1.data/data/include/rapidcheck.h
pyterrier_pisa-0.3.1.data/data/include/rapidcheck/Maybe.hpp
pyterrier_pisa-0.3.1.data/data/include/rapidcheck/Shrinkable.h
pyterrier_pisa-0.3.1.data/data/include/rapidcheck/Show.h
pyterrier_pisa-0.3.1.data/data/include/rapidcheck/Seq.hpp
pyterrier_pisa-0.3.1.data/data/include/rapidcheck/Random.h
pyterrier_pisa-0.3.1.data/data/include/rapidcheck/Seq.h
pyterrier_pisa-0.3.1.data/data/include/rapidcheck/Compat.h
pyterrier_pisa-0.3.1.data/data/include/rapidcheck/Maybe.h
pyterrier_pisa-0.3.1.data/data/include/rapidcheck/Random.hpp
pyterrier_pisa-0.3.1.data/data/include/rapidcheck/Log.hpp
pyterrier_pisa-0.3.1.data/data/include/rapidcheck/Show.hpp
pyterrier_pisa-0.3.1.data/data/include/rapidcheck/Shrinkable.hpp
pyterrier_pisa-0.3.1.data/data/include/rapidcheck/Nothing.h
pyterrier_pisa-0.3.1.data/data/include/rapidcheck/Assertions.h
pyterrier_pisa-0.3.1.data/data/include/rapidcheck/Gen.hpp
pyterrier_pisa-0.3.1.data/data/include/rapidcheck/Traits.h
pyterrier_pisa-0.3.1.data/data/include/rapidcheck/Classify.h
pyterrier_pisa-0.3.1.data/data/include/rapidcheck/Gen.h
pyterrier_pisa-0.3.1.data/data/include/rapidcheck/BeforeMinimalTestCase.h
pyterrier_pisa-0.3.1.data/data/include/rapidcheck/Check.h
