Metadata-Version: 2.1
Name: pyterrier_pisa
Version: 0.3.1
Summary: A PyTerrier interface to the PISA search engine
Author: Sean MacAvaney
Requires-Python: >=3.8
License-File: LICENSE
Requires-Dist: python-terrier>=0.9.1
Requires-Dist: pyterrier-alpha>=0.2.0
Requires-Dist: numpy<2.0.0,>=1.21.0
Requires-Dist: tqdm
Requires-Dist: tbb<=2020.3.254
Requires-Dist: enum-tools
Provides-Extra: ciff
Requires-Dist: pyciff==0.1.1; extra == "ciff"
